sparrow_static/__init__.py
sparrow_static/__main__.py
sparrow_static/create_static_site.py
sparrow_static-0.1.1.dist-info/METADATA
sparrow_static-0.1.1.dist-info/WHEEL
sparrow_static-0.1.1.dist-info/entry_points.txt
sparrow_static-0.1.1.dist-info/top_level.txt
sparrow_static-0.1.1.dist-info/RECORD
