Metadata-Version: 2.1
Name: sparrow-static
Version: 0.1.1
Author: Sparrow Computing
Author-email: ben@sparrow.dev
Requires-Dist: boto3
Requires-Dist: fire
Provides-Extra: dev
Requires-Dist: jupyter; extra == "dev"
Requires-Dist: pytest; extra == "dev"
Requires-Dist: pytest-cov; extra == "dev"
Requires-Dist: uv; extra == "dev"
